{
    "penguin": {
        "blue": "0x003366",
        "green": "0x009900",
        "pink": "0xFF3399",
        "black": "0x333333",
        "red": "0xCC0000",
        "orange": "0xFF6600",
        "yellow": "0xFFCC00",
        "dark purple": "0x660099",
        "brown": "0x996600",
        "peach": "0xFF6666",
        "dark green": "0x006600",
        "light blue": "0x0099CC",
        "light green": "0x8AE302",
        "aqua": "0x02A797",
        "arctic white": "0xF0F0D8",
        "pure black": "0x000000",
        "maroon": "0x80214B",
        "lavender": "0xAE9FC8"
    },
    "belt": {
        "white": "0xFFFFFF",
        "yellow": "0xFFFF00",
        "orange": "0xFF6600",
        "green": "0x33CC00",
        "blue": "0x0033CC",
        "red": "0xCC0000",
        "purple": "0x6600FF",
        "brown": "0x663300",
        "black": "0x444444"
    },
    "card": {
        "blue": {
            "hex": "0x1148A1",
            "glow": { "ra": 55, "rb": 12, "ga": 55, "gb": 41, "ba": 55, "bb": 158, "aa": 80, "ab": 0 }
        },
        "purple": {
            "hex": "0xA399CA",
            "glow": { "ra": 45, "rb": 102, "ga": 45, "gb": 77, "ba": 45, "bb": 101, "aa": 80, "ab": 0 }
        },
        "green": {
            "hex": "0x61B946",
            "glow": { "ra": 50, "rb:": 49, "ga": 50, "gb": 93, "ba": 50, "bb": 35, "aa": 80, "ab": 0 }
        },
        "orange": {
            "hex": "0xF7952B",
            "glow": { "ra": 45, "rb": 153, "ga": 45, "gb": 86, "ba": 45, "bb": 15, "aa": 80, "ab": 0 }
        },
        "red": {
            "hex": "0xE23C26",
            "glow": { "ra": 45, "rb": 153, "ga": 45, "gb": 30, "ba": 45, "bb": 5, "aa": 80, "ab": 0 }
        },
        "yellow": {
            "hex": "0xFBEB2D",
            "glow": { "ra": 35, "rb": 150, "ga": 35, "gb": 153, "ba": 35, "bb": 15, "aa": 80, "ab": 0 }
        }
    }
}